hindsight_api/__init__.py
hindsight_api/banner.py
hindsight_api/config.py
hindsight_api/daemon.py
hindsight_api/main.py
hindsight_api/mcp_local.py
hindsight_api/mcp_tools.py
hindsight_api/metrics.py
hindsight_api/migrations.py
hindsight_api/models.py
hindsight_api/pg0.py
hindsight_api/server.py
hindsight_api/admin/__init__.py
hindsight_api/admin/cli.py
hindsight_api/alembic/README
hindsight_api/alembic/env.py
hindsight_api/alembic/script.py.mako
hindsight_api/alembic/versions/5a366d414dce_initial_schema.py
hindsight_api/alembic/versions/b7c4d8e9f1a2_add_chunks_table.py
hindsight_api/alembic/versions/c8e5f2a3b4d1_add_retain_params_to_documents.py
hindsight_api/alembic/versions/d9f6a3b4c5e2_rename_bank_to_interactions.py
hindsight_api/alembic/versions/e0a1b2c3d4e5_disposition_to_3_traits.py
hindsight_api/alembic/versions/f1a2b3c4d5e6_add_memory_links_composite_index.py
hindsight_api/alembic/versions/g2a3b4c5d6e7_add_tags_column.py
hindsight_api/alembic/versions/h3c4d5e6f7g8_mental_models_v4.py
hindsight_api/alembic/versions/i4d5e6f7g8h9_delete_opinions.py
hindsight_api/alembic/versions/j5e6f7g8h9i0_mental_model_versions.py
hindsight_api/alembic/versions/k6f7g8h9i0j1_add_directive_subtype.py
hindsight_api/alembic/versions/l7g8h9i0j1k2_add_worker_columns.py
hindsight_api/alembic/versions/m8h9i0j1k2l3_mental_model_id_to_text.py
hindsight_api/alembic/versions/n9i0j1k2l3m4_learnings_and_pinned_reflections.py
hindsight_api/alembic/versions/o0j1k2l3m4n5_migrate_mental_models_data.py
hindsight_api/alembic/versions/p1k2l3m4n5o6_new_knowledge_architecture.py
hindsight_api/alembic/versions/q2l3m4n5o6p7_fix_mental_model_fact_type.py
hindsight_api/alembic/versions/r3m4n5o6p7q8_add_reflect_response_to_reflections.py
hindsight_api/alembic/versions/rename_personality_to_disposition.py
hindsight_api/alembic/versions/s4n5o6p7q8r9_add_consolidated_at_to_memory_units.py
hindsight_api/alembic/versions/t5o6p7q8r9s0_rename_mental_models_to_observations.py
hindsight_api-0.4.7.dist-info/METADATA
hindsight_api-0.4.7.dist-info/WHEEL
hindsight_api-0.4.7.dist-info/entry_points.txt
hindsight_api-0.4.7.dist-info/RECORD
