Metadata-Version: 2.4
Name: hindsight-api
Version: 0.4.7
Summary: Hindsight: Agent Memory That Works Like Human Memory
Requires-Python: >=3.11
Requires-Dist: aiohttp>=3.13.3
Requires-Dist: alembic>=1.17.1
Requires-Dist: anthropic>=0.40.0
Requires-Dist: asyncpg>=0.29.0
Requires-Dist: authlib>=1.6.6
Requires-Dist: cohere>=5.0.0
Requires-Dist: dateparser>=1.2.2
Requires-Dist: fastapi[standard]>=0.120.3
Requires-Dist: fastmcp>=2.14.0
Requires-Dist: filelock>=3.20.1
Requires-Dist: flashrank>=0.2.0
Requires-Dist: google-auth>=2.0.0
Requires-Dist: google-genai>=1.0.0
Requires-Dist: greenlet>=3.2.4
Requires-Dist: httpx>=0.27.0
Requires-Dist: langchain-core>=1.2.5
Requires-Dist: langchain-text-splitters>=0.3.0
Requires-Dist: openai>=1.0.0
Requires-Dist: opentelemetry-api>=1.20.0
Requires-Dist: opentelemetry-exporter-prometheus>=0.41b0
Requires-Dist: opentelemetry-instrumentation-fastapi>=0.41b0
Requires-Dist: opentelemetry-sdk>=1.20.0
Requires-Dist: pg0-embedded>=0.11.0
Requires-Dist: pgvector>=0.4.1
Requires-Dist: psycopg2-binary>=2.9.11
Requires-Dist: pyasn1>=0.6.2
Requires-Dist: pydantic>=2.0.0
Requires-Dist: python-dateutil>=2.8.0
Requires-Dist: python-dotenv>=1.0.0
Requires-Dist: rich>=13.0.0
Requires-Dist: sentence-transformers>=3.3.0
Requires-Dist: sqlalchemy>=2.0.44
Requires-Dist: tiktoken>=0.12.0
Requires-Dist: torch>=2.6.0
Requires-Dist: transformers>=4.53.0
Requires-Dist: typer>=0.9.0
Requires-Dist: urllib3>=2.6.3
Requires-Dist: uvicorn>=0.38.0
Requires-Dist: uvloop>=0.22.1
Requires-Dist: wsproto>=1.0.0
Provides-Extra: test
Requires-Dist: filelock>=3.20.1; extra == 'test'
Requires-Dist: pytest-asyncio>=0.21.0; extra == 'test'
Requires-Dist: pytest-timeout>=2.4.0; extra == 'test'
Requires-Dist: pytest-xdist>=3.0.0; extra == 'test'
Requires-Dist: pytest>=7.0.0; extra == 'test'
